.clickbank.tmproj
.svnignore
.vimrc
README.txt
buildout.cfg
setup.cfg
setup.py
buildout/bootstrap.py
buildout/buildout.cfg
docs/.svnignore
docs/HISTORY.txt
docs/INSTALL.txt
docs/LICENSE.GPL
docs/LICENSE.txt
docs/source/conf.py
docs/source/index.rst
niteoweb/__init__.py
niteoweb.clickbank.egg-info/PKG-INFO
niteoweb.clickbank.egg-info/SOURCES.txt
niteoweb.clickbank.egg-info/dependency_links.txt
niteoweb.clickbank.egg-info/entry_points.txt
niteoweb.clickbank.egg-info/namespace_packages.txt
niteoweb.clickbank.egg-info/not-zip-safe
niteoweb.clickbank.egg-info/requires.txt
niteoweb.clickbank.egg-info/top_level.txt
niteoweb/clickbank/__init__.py
niteoweb/clickbank/clickbank_settings.py
niteoweb/clickbank/config.py
niteoweb/clickbank/configure.zcml
niteoweb/clickbank/interfaces.py
niteoweb/clickbank/browser/__init__.py
niteoweb/clickbank/browser/clickbank.py
niteoweb/clickbank/browser/clickbank_icon.png
niteoweb/clickbank/browser/configure.zcml
niteoweb/clickbank/browser/configure_clickbank.py
niteoweb/clickbank/browser/email.pt
niteoweb/clickbank/profiles/default/componentregistry.xml
niteoweb/clickbank/profiles/default/controlpanel.xml
niteoweb/clickbank/profiles/default/memberdata_properties.xml
niteoweb/clickbank/profiles/default/propertiestool.xml
niteoweb/clickbank/profiles/default/rolemap.xml
niteoweb/clickbank/profiles/uninstall/componentregistry.xml
niteoweb/clickbank/profiles/uninstall/controlpanel.xml
niteoweb/clickbank/profiles/uninstall/memberdata_properties.xml
niteoweb/clickbank/tests/__init__.py
niteoweb/clickbank/tests/control_panel.txt
niteoweb/clickbank/tests/test_clickbank.py
niteoweb/clickbank/tests/test_doctest.py
niteoweb/clickbank/tests/test_setup.py