Metadata-Version: 1.0
Name: niteoweb.clickbank
Version: 0.5.1
Summary: Integrates ClickBank digital products retailer system with Plone for paid memberships.
Home-page: http://svn.plone.org/svn/collective/niteoweb.clickbank
Author: NiteoWeb Ltd.
Author-email: info@niteoweb.com
License: GPL
Keywords: plone clickbank
Platform: UNKNOWN
Classifier: Development Status :: 4 - Beta
Classifier: Framework :: Plone
Classifier: Programming Language :: Python
